uml_interpreter/__init__.py
uml_interpreter/consistency_checker/__init__.py
uml_interpreter/consistency_checker/consistency_checker.py
uml_interpreter/deserializer/__init__.py
uml_interpreter/deserializer/abstract.py
uml_interpreter/deserializer/enterprise_architect/__init__.py
uml_interpreter/deserializer/enterprise_architect/constants.py
uml_interpreter/deserializer/enterprise_architect/ea_xml_deserializer.py
uml_interpreter/deserializer/enterprise_architect/uml_object_builders/uml_class_builder.py
uml_interpreter/deserializer/enterprise_architect/uml_object_builders/uml_sequence_builder.py
uml_interpreter/deserializer/enterprise_architect/utils.py
uml_interpreter/deserializer/errors.py
uml_interpreter/model/__init__.py
uml_interpreter/model/abstract.py
uml_interpreter/model/diagrams/__init__.py
uml_interpreter/model/diagrams/abstract.py
uml_interpreter/model/diagrams/class_diagram.py
uml_interpreter/model/diagrams/component_diagram.py
uml_interpreter/model/diagrams/sequence_diagram.py
uml_interpreter/model/errors.py
uml_interpreter/model/model.py
uml_interpreter/serializer/__init__.py
uml_interpreter/serializer/abstract.py
uml_interpreter/serializer/enterprise_architect/__init__.py
uml_interpreter/serializer/enterprise_architect/constants.py
uml_interpreter/serializer/enterprise_architect/ea_xml_serializer.py
uml_interpreter/serializer/errors.py
uml_interpreter/source/__init__.py
uml_interpreter/source/abstract.py
uml_interpreter/source/source.py
uml_interpreter/visitor/__init__.py
uml_interpreter/visitor/model_visitor.py
uml_interpreter-1.0.0.dist-info/LICENSE
uml_interpreter-1.0.0.dist-info/METADATA
uml_interpreter-1.0.0.dist-info/WHEEL
uml_interpreter-1.0.0.dist-info/RECORD
